electrumsv_bsor/__init__.py
electrumsv_bsor/core.py
electrumsv_bsor-0.9.dist-info/LICENCE
electrumsv_bsor-0.9.dist-info/METADATA
electrumsv_bsor-0.9.dist-info/WHEEL
electrumsv_bsor-0.9.dist-info/top_level.txt
electrumsv_bsor-0.9.dist-info/RECORD
