Metadata-Version: 2.1
Name: electrumsv-bsor
Version: 0.9
Summary: A BSOR encoding/decoding library.
Home-page: https://github.com/electrumsv/electrumsv-bsor
Author: Roger Taylor
Author-email: roger.taylor.email@gmail.com
License: Open BSV License
License-File: LICENCE
